[
    {
        "flight_number": "SU1869",
        "aircraft_model": "",
        "airline_name": "Aeroflot",
        "destination_iata": "SVO",
        "local_departure_time": "00:15",
        "local_arrival_time": "02:50",
        "duration": "03:35",
        "destination_airport_name": "Moscow Sheremetyevo International Airport",
        "destination_city": "Moscow",
        "destination_country": "Russia"
    },
    {
        "flight_number": "U62634",
        "aircraft_model": "",
        "airline_name": "Ural Airlines",
        "destination_iata": "DME",
        "local_departure_time": "00:45",
        "local_arrival_time": "02:55",
        "duration": "03:10",
        "destination_airport_name": "Moscow Domodedovo International Airport",
        "destination_city": "Moscow",
        "destination_country": "Russia"
    },
    {
        "flight_number": "SN2900",
        "aircraft_model": "Airbus A320-214",
        "airline_name": "Brussels Airlines",
        "destination_iata": "BRU",
        "local_departure_time": "00:50",
        "local_arrival_time": "03:40",
        "duration": "04:50",
        "destination_airport_name": "Brussels Airport",
        "destination_city": "Brussels",
        "destination_country": "Belgium"
    },
    {
        "flight_number": "JI100",
        "aircraft_model": "",
        "airline_name": "Armenian Airlines",
        "destination_iata": "SVO",
        "local_departure_time": "02:15",
        "local_arrival_time": "04:40",
        "duration": "03:25",
        "destination_airport_name": "Moscow Sheremetyevo International Airport",
        "destination_city": "Moscow",
        "destination_country": "Russia"
    },
    {
        "flight_number": "UT786",
        "aircraft_model": "",
        "airline_name": "Utair",
        "destination_iata": "VKO",
        "local_departure_time": "02:45",
        "local_arrival_time": "05:20",
        "duration": "03:35",
        "destination_airport_name": "Moscow Vnukovo International Airport",
        "destination_city": "Moscow",
        "destination_country": "Russia"
    },
    {
        "flight_number": "DE4338",
        "aircraft_model": "Airbus A319-112",
        "airline_name": "Condor",
        "destination_iata": "FRA",
        "local_departure_time": "02:50",
        "local_arrival_time": "05:25",
        "duration": "04:35",
        "destination_airport_name": "Frankfurt Airport",
        "destination_city": "Frankfurt",
        "destination_country": "Germany"
    },
    {
        "flight_number": "QR286",
        "aircraft_model": "Airbus A320-232",
        "airline_name": "Qatar Airways",
        "destination_iata": "DOH",
        "local_departure_time": "03:20",
        "local_arrival_time": "05:10",
        "duration": "02:50",
        "destination_airport_name": "Doha Hamad International Airport",
        "destination_city": "Doha",
        "destination_country": "Qatar"
    },
    {
        "flight_number": "GQ781",
        "aircraft_model": "Airbus A320-251N",
        "airline_name": "SKY express",
        "destination_iata": "ATH",
        "local_departure_time": "03:45",
        "local_arrival_time": "05:45",
        "duration": "03:00",
        "destination_airport_name": "Athens Eleftherios Venizelos",
        "destination_city": "Athens",
        "destination_country": "Greece"
    },
    {
        "flight_number": "4S1262",
        "aircraft_model": "",
        "airline_name": "Red Sea Airlines",
        "destination_iata": "SSH",
        "local_departure_time": "03:45",
        "local_arrival_time": "06:45",
        "duration": "04:00",
        "destination_airport_name": "Sharm el-Sheikh International Airport",
        "destination_city": "Sharm el-Sheikh",
        "destination_country": "Egypt"
    },
    {
        "flight_number": "A3899",
        "aircraft_model": "Airbus A320-271N",
        "airline_name": "Aegean Airlines",
        "destination_iata": "ATH",
        "local_departure_time": "04:20",
        "local_arrival_time": "06:15",
        "duration": "02:55",
        "destination_airport_name": "Athens Eleftherios Venizelos",
        "destination_city": "Athens",
        "destination_country": "Greece"
    },
    {
        "flight_number": "LO728",
        "aircraft_model": "",
        "airline_name": "LOT",
        "destination_iata": "WAW",
        "local_departure_time": "04:20",
        "local_arrival_time": "06:15",
        "duration": "03:55",
        "destination_airport_name": "Warsaw Chopin Airport",
        "destination_city": "Warsaw",
        "destination_country": "Poland"
    },
    {
        "flight_number": "LH1561",
        "aircraft_model": "Airbus A320-271N",
        "airline_name": "Lufthansa",
        "destination_iata": "FRA",
        "local_departure_time": "04:35",
        "local_arrival_time": "07:15",
        "duration": "04:40",
        "destination_airport_name": "Frankfurt Airport",
        "destination_city": "Frankfurt",
        "destination_country": "Germany"
    },
    {
        "flight_number": "OS642",
        "aircraft_model": "Airbus A320-214",
        "airline_name": "Austrian Airlines",
        "destination_iata": "VIE",
        "local_departure_time": "04:45",
        "local_arrival_time": "06:30",
        "duration": "03:45",
        "destination_airport_name": "Vienna International Airport",
        "destination_city": "Vienna",
        "destination_country": "Austria"
    },
    {
        "flight_number": "GQ781",
        "aircraft_model": "Airbus A320-251N",
        "airline_name": "SKY express",
        "destination_iata": "ATH",
        "local_departure_time": "05:00",
        "local_arrival_time": "07:00",
        "duration": "03:00",
        "destination_airport_name": "Athens Eleftherios Venizelos",
        "destination_city": "Athens",
        "destination_country": "Greece"
    },
    {
        "flight_number": "LO730",
        "aircraft_model": "Boeing 737-86N",
        "airline_name": "LOT",
        "destination_iata": "WAW",
        "local_departure_time": "05:30",
        "local_arrival_time": "07:25",
        "duration": "03:55",
        "destination_airport_name": "Warsaw Chopin Airport",
        "destination_city": "Warsaw",
        "destination_country": "Poland"
    },
    {
        "flight_number": "EW8995",
        "aircraft_model": "",
        "airline_name": "Eurowings",
        "destination_iata": "BER",
        "local_departure_time": "05:30",
        "local_arrival_time": "07:55",
        "duration": "04:25",
        "destination_airport_name": "Berlin Brandenburg Airport",
        "destination_city": "Berlin",
        "destination_country": "Germany"
    },
    {
        "flight_number": "B2734",
        "aircraft_model": "",
        "airline_name": "Belavia",
        "destination_iata": "MSQ",
        "local_departure_time": "05:55",
        "local_arrival_time": "08:55",
        "duration": "04:00",
        "destination_airport_name": "Minsk National Airport",
        "destination_city": "Minsk",
        "destination_country": "Belarus"
    },
    {
        "flight_number": "3F333",
        "aircraft_model": "",
        "airline_name": "FlyOne Armenia",
        "destination_iata": "LED",
        "local_departure_time": "06:00",
        "local_arrival_time": "08:50",
        "duration": "03:50",
        "destination_airport_name": "St. Petersburg Pulkovo Airport",
        "destination_city": "St. Petersburg",
        "destination_country": "Russia"
    },
    {
        "flight_number": "PC551",
        "aircraft_model": "",
        "airline_name": "Pegasus",
        "destination_iata": "SAW",
        "local_departure_time": "06:00",
        "local_arrival_time": "07:30",
        "duration": "02:30",
        "destination_airport_name": "Istanbul Sabiha Gokcen International Airport",
        "destination_city": "Istanbul",
        "destination_country": "Turkey"
    },
    {
        "flight_number": "3F321",
        "aircraft_model": "",
        "airline_name": "FlyOne Armenia",
        "destination_iata": "VKO",
        "local_departure_time": "06:10",
        "local_arrival_time": "08:30",
        "duration": "03:20",
        "destination_airport_name": "Moscow Vnukovo International Airport",
        "destination_city": "Moscow",
        "destination_country": "Russia"
    },
    {
        "flight_number": "3F477",
        "aircraft_model": "",
        "airline_name": "FlyOne Armenia",
        "destination_iata": "SVX",
        "local_departure_time": "06:20",
        "local_arrival_time": "10:40",
        "duration": "03:20",
        "destination_airport_name": "Yekaterinburg Koltsovo International Airport",
        "destination_city": "Yekaterinburg",
        "destination_country": "Russia"
    },
    {
        "flight_number": "PC551",
        "aircraft_model": "",
        "airline_name": "Pegasus",
        "destination_iata": "SAW",
        "local_departure_time": "06:30",
        "local_arrival_time": "08:00",
        "duration": "02:30",
        "destination_airport_name": "Istanbul Sabiha Gokcen International Airport",
        "destination_city": "Istanbul",
        "destination_country": "Turkey"
    },
    {
        "flight_number": "W62464",
        "aircraft_model": "Airbus A321-271NX",
        "airline_name": "Wizz Air",
        "destination_iata": "BUD",
        "local_departure_time": "06:40",
        "local_arrival_time": "07:55",
        "duration": "03:15",
        "destination_airport_name": "Budapest Ferenc Liszt International Airport",
        "destination_city": "Budapest",
        "destination_country": "Hungary"
    },
    {
        "flight_number": "SU1967",
        "aircraft_model": "",
        "airline_name": "Aeroflot",
        "destination_iata": "SVO",
        "local_departure_time": "06:45",
        "local_arrival_time": "09:05",
        "duration": "03:20",
        "destination_airport_name": "Moscow Sheremetyevo International Airport",
        "destination_city": "Moscow",
        "destination_country": "Russia"
    },
    {
        "flight_number": "3F321",
        "aircraft_model": "Airbus A320-233",
        "airline_name": "FlyOne",
        "destination_iata": "VKO",
        "local_departure_time": "07:10",
        "local_arrival_time": "09:10",
        "duration": "03:00",
        "destination_airport_name": "Moscow Vnukovo International Airport",
        "destination_city": "Moscow",
        "destination_country": "Russia"
    },
    {
        "flight_number": "SM994",
        "aircraft_model": "",
        "airline_name": "Air Cairo",
        "destination_iata": "SSH",
        "local_departure_time": "07:10",
        "local_arrival_time": "09:20",
        "duration": "03:10",
        "destination_airport_name": "Sharm el-Sheikh International Airport",
        "destination_city": "Sharm el-Sheikh",
        "destination_country": "Egypt"
    },
    {
        "flight_number": "3F477",
        "aircraft_model": "",
        "airline_name": "FlyOne Armenia",
        "destination_iata": "SVX",
        "local_departure_time": "07:25",
        "local_arrival_time": "11:45",
        "duration": "03:20",
        "destination_airport_name": "Yekaterinburg Koltsovo International Airport",
        "destination_city": "Yekaterinburg",
        "destination_country": "Russia"
    },
    {
        "flight_number": "3F311",
        "aircraft_model": "",
        "airline_name": "FlyOne Armenia",
        "destination_iata": "DME",
        "destination_airport_name": "Moscow Domodedovo International Airport",
        "destination_city": "Moscow",
        "destination_country": "Russia",
        "local_departure_time": "07:40",
        "local_arrival_time": "09:40",
        "duration": "03:00"
    },
    {
        "flight_number": "AF1061",
        "aircraft_model": "",
        "airline_name": "Air France",
        "destination_iata": "CDG",
        "local_departure_time": "08:00",
        "local_arrival_time": "11:15",
        "duration": "05:15",
        "destination_airport_name": "Paris Charles de Gaulle Airport",
        "destination_city": "Paris",
        "destination_country": "France"
    },
    {
        "flight_number": "AF1061",
        "aircraft_model": "Airbus A320-214",
        "airline_name": "Air France",
        "destination_iata": "CDG",
        "local_departure_time": "08:40",
        "local_arrival_time": "11:55",
        "duration": "05:15",
        "destination_airport_name": "Paris Charles de Gaulle Airport",
        "destination_city": "Paris",
        "destination_country": "France"
    },
    {
        "flight_number": "3F871",
        "aircraft_model": "",
        "airline_name": "FlyOne Armenia",
        "destination_iata": "LCA",
        "local_departure_time": "08:40",
        "local_arrival_time": "09:50",
        "duration": "02:10",
        "destination_airport_name": "Larnaca International Airport",
        "destination_city": "Larnaca",
        "destination_country": "Cyprus"
    },
    {
        "flight_number": "WZ4330",
        "aircraft_model": "",
        "airline_name": "Red Wings",
        "destination_iata": "AER",
        "local_departure_time": "09:00",
        "local_arrival_time": "09:30",
        "duration": "01:30",
        "destination_airport_name": "Sochi International Airport",
        "destination_city": "Sochi",
        "destination_country": "Russia"
    },
    {
        "flight_number": "3F873",
        "aircraft_model": "",
        "airline_name": "FlyOne Armenia",
        "destination_iata": "TLV",
        "local_departure_time": "09:05",
        "local_arrival_time": "10:50",
        "duration": "02:45",
        "destination_airport_name": "Tel Aviv Ben Gurion International Airport",
        "destination_city": "Tel Aviv",
        "destination_country": "Israel"
    },
    {
        "flight_number": "5G509",
        "aircraft_model": "",
        "airline_name": "Shirak Avia",
        "destination_iata": "VKO",
        "local_departure_time": "09:30",
        "local_arrival_time": "11:50",
        "duration": "03:20",
        "destination_airport_name": "Moscow Vnukovo International Airport",
        "destination_city": "Moscow",
        "destination_country": "Russia"
    },
    {
        "flight_number": null,
        "aircraft_model": "Boeing 737-86N",
        "airline_name": "Shirak Avia",
        "destination_iata": "VKO",
        "local_departure_time": "09:30",
        "local_arrival_time": "11:36",
        "duration": "03:06",
        "destination_airport_name": "Moscow Vnukovo International Airport",
        "destination_city": "Moscow",
        "destination_country": "Russia"
    },
    {
        "flight_number": null,
        "aircraft_model": "Boeing 737-86N",
        "airline_name": "Shirak Avia",
        "destination_iata": "VKO",
        "destination_airport_name": "Moscow Vnukovo International Airport",
        "destination_city": "Moscow",
        "destination_country": "Russia",
        "local_departure_time": "09:30",
        "local_arrival_time": "11:25",
        "duration": "02:55"
    },
    {
        "flight_number": "A9724",
        "aircraft_model": "",
        "airline_name": "Georgian Airways",
        "destination_iata": "TBS",
        "local_departure_time": "10:00",
        "local_arrival_time": "10:30",
        "duration": "00:30",
        "destination_airport_name": "Tbilisi International Airport",
        "destination_city": "Tbilisi",
        "destination_country": "Georgia"
    },
    {
        "flight_number": "Y5133",
        "aircraft_model": "",
        "airline_name": "Hayways",
        "destination_iata": "VKO",
        "local_departure_time": "10:00",
        "local_arrival_time": "12:20",
        "duration": "03:20",
        "destination_airport_name": "Moscow Vnukovo International Airport",
        "destination_city": "Moscow",
        "destination_country": "Russia"
    },
    {
        "flight_number": "U62704",
        "aircraft_model": "",
        "airline_name": "Ural Airlines",
        "destination_iata": "DME",
        "local_departure_time": "10:05",
        "local_arrival_time": "12:20",
        "duration": "03:15",
        "destination_airport_name": "Moscow Domodedovo International Airport",
        "destination_city": "Moscow",
        "destination_country": "Russia"
    },
    {
        "flight_number": "ME276",
        "aircraft_model": "",
        "airline_name": "MEA",
        "destination_iata": "BEY",
        "local_departure_time": "10:10",
        "local_arrival_time": "11:10",
        "duration": "02:00",
        "destination_airport_name": "Beirut Rafic Hariri International Airport",
        "destination_city": "Beirut",
        "destination_country": "Lebanon"
    },
    {
        "flight_number": "5W7014",
        "aircraft_model": "Airbus A321-231",
        "airline_name": "Wizz Air",
        "destination_iata": "AUH",
        "local_departure_time": "10:20",
        "local_arrival_time": "13:30",
        "duration": "03:10",
        "destination_airport_name": "Abu Dhabi Zayed International Airport",
        "destination_city": "Abu Dhabi",
        "destination_country": "United Arab Emirates"
    },
    {
        "flight_number": "U62704",
        "aircraft_model": "",
        "airline_name": "Ural Airlines",
        "destination_iata": "DME",
        "local_departure_time": "10:50",
        "local_arrival_time": "13:05",
        "duration": "03:15",
        "destination_airport_name": "Moscow Domodedovo International Airport",
        "destination_city": "Moscow",
        "destination_country": "Russia"
    },
    {
        "flight_number": "6A221",
        "aircraft_model": "",
        "airline_name": "Armenia Airways",
        "destination_iata": "IKA",
        "local_departure_time": "11:10",
        "local_arrival_time": "12:10",
        "duration": "01:30",
        "destination_airport_name": "Tehran Imam Khomeini International Airport",
        "destination_city": "Tehran",
        "destination_country": "Iran"
    },
    {
        "flight_number": "A45030",
        "aircraft_model": "",
        "airline_name": "Azimuth",
        "destination_iata": "AER",
        "local_departure_time": "11:10",
        "local_arrival_time": "12:00",
        "duration": "01:50",
        "destination_airport_name": "Sochi International Airport",
        "destination_city": "Sochi",
        "destination_country": "Russia"
    },
    {
        "flight_number": "A45030",
        "aircraft_model": "",
        "airline_name": "Azimuth",
        "destination_iata": "AER",
        "local_departure_time": "11:10",
        "local_arrival_time": "11:30",
        "duration": "01:20",
        "destination_airport_name": "Sochi International Airport",
        "destination_city": "Sochi",
        "destination_country": "Russia"
    },
    {
        "flight_number": "5G509",
        "aircraft_model": "",
        "airline_name": "Shirak Avia",
        "destination_iata": "VKO",
        "local_departure_time": "11:15",
        "local_arrival_time": "13:35",
        "duration": "03:20",
        "destination_airport_name": "Moscow Vnukovo International Airport",
        "destination_city": "Moscow",
        "destination_country": "Russia"
    },
    {
        "flight_number": "SU6720",
        "aircraft_model": "",
        "airline_name": "Aeroflot",
        "destination_iata": "AER",
        "local_departure_time": "11:50",
        "local_arrival_time": "12:30",
        "duration": "01:40",
        "destination_airport_name": "Sochi International Airport",
        "destination_city": "Sochi",
        "destination_country": "Russia"
    },
    {
        "flight_number": "SU6720",
        "aircraft_model": "",
        "airline_name": "Aeroflot",
        "destination_iata": "AER",
        "local_departure_time": "11:55",
        "local_arrival_time": "12:40",
        "duration": "01:45",
        "destination_airport_name": "Sochi International Airport",
        "destination_city": "Sochi",
        "destination_country": "Russia"
    },
    {
        "flight_number": "G9247",
        "aircraft_model": "",
        "airline_name": "Air Arabia",
        "destination_iata": "SHJ",
        "local_departure_time": "12:00",
        "local_arrival_time": "14:55",
        "duration": "02:55",
        "destination_airport_name": "Sharjah International Airport",
        "destination_city": "Sharjah",
        "destination_country": "United Arab Emirates"
    },
    {
        "flight_number": null,
        "aircraft_model": "Dassault Falcon 2000EX",
        "airline_name": "NetJets Europe",
        "destination_iata": "ATH",
        "local_departure_time": "12:00",
        "local_arrival_time": "13:40",
        "duration": "02:40",
        "destination_airport_name": "Athens Eleftherios Venizelos",
        "destination_city": "Athens",
        "destination_country": "Greece"
    },
    {
        "flight_number": "6A221",
        "aircraft_model": "",
        "airline_name": "Armenia Airways",
        "destination_iata": "IKA",
        "local_departure_time": "12:00",
        "local_arrival_time": "13:00",
        "duration": "01:30",
        "destination_airport_name": "Tehran Imam Khomeini International Airport",
        "destination_city": "Tehran",
        "destination_country": "Iran"
    },
    {
        "flight_number": "W42892",
        "aircraft_model": "",
        "airline_name": "Wizz Air Malta",
        "destination_iata": "VIE",
        "local_departure_time": "12:05",
        "local_arrival_time": "13:55",
        "duration": "03:50",
        "destination_airport_name": "Vienna International Airport",
        "destination_city": "Vienna",
        "destination_country": "Austria"
    },
    {
        "flight_number": "SU6720",
        "aircraft_model": "",
        "airline_name": "Aeroflot",
        "destination_iata": "AER",
        "local_departure_time": "12:10",
        "local_arrival_time": "12:30",
        "duration": "01:20",
        "destination_airport_name": "Sochi International Airport",
        "destination_city": "Sochi",
        "destination_country": "Russia"
    },
    {
        "flight_number": "FZ718",
        "aircraft_model": "",
        "airline_name": "flydubai",
        "destination_iata": "DXB",
        "local_departure_time": "12:25",
        "local_arrival_time": "15:30",
        "duration": "03:05",
        "destination_airport_name": "Dubai International Airport",
        "destination_city": "Dubai",
        "destination_country": "United Arab Emirates"
    },
    {
        "flight_number": "W46168",
        "aircraft_model": "Airbus A321-271NX",
        "airline_name": "Wizz Air",
        "destination_iata": "FCO",
        "local_departure_time": "12:40",
        "local_arrival_time": "14:55",
        "duration": "04:15",
        "destination_airport_name": "Rome Leonardo da Vinci Fiumicino Airport",
        "destination_city": "Rome",
        "destination_country": "Italy"
    },
    {
        "flight_number": "JI122",
        "aircraft_model": "",
        "airline_name": "Armenian Airlines",
        "destination_iata": "AER",
        "local_departure_time": "12:45",
        "local_arrival_time": "13:00",
        "duration": "01:15",
        "destination_airport_name": "Sochi International Airport",
        "destination_city": "Sochi",
        "destination_country": "Russia"
    },
    {
        "flight_number": "W46168",
        "aircraft_model": "",
        "airline_name": "Wizz Air Malta",
        "destination_iata": "FCO",
        "local_departure_time": "12:55",
        "local_arrival_time": "15:10",
        "duration": "04:15",
        "destination_airport_name": "Rome Leonardo da Vinci Fiumicino Airport",
        "destination_city": "Rome",
        "destination_country": "Italy"
    },
    {
        "flight_number": "SU1861",
        "aircraft_model": "",
        "airline_name": "Aeroflot",
        "destination_iata": "SVO",
        "local_departure_time": "13:55",
        "local_arrival_time": "16:25",
        "duration": "03:30",
        "destination_airport_name": "Moscow Sheremetyevo International Airport",
        "destination_city": "Moscow",
        "destination_country": "Russia"
    },
    {
        "flight_number": "SU1861",
        "aircraft_model": "",
        "airline_name": "Aeroflot",
        "destination_iata": "SVO",
        "local_departure_time": "13:55",
        "local_arrival_time": "16:20",
        "duration": "03:25",
        "destination_airport_name": "Moscow Sheremetyevo International Airport",
        "destination_city": "Moscow",
        "destination_country": "Russia"
    },
    {
        "flight_number": "W64566",
        "aircraft_model": "Airbus A321-231",
        "airline_name": "Wizz Air",
        "destination_iata": "LCA",
        "local_departure_time": "14:00",
        "local_arrival_time": "15:30",
        "duration": "02:30",
        "destination_airport_name": "Larnaca International Airport",
        "destination_city": "Larnaca",
        "destination_country": "Cyprus"
    },
    {
        "flight_number": "IS7327",
        "aircraft_model": "",
        "airline_name": "Sepehran Airlines",
        "destination_iata": "IKA",
        "local_departure_time": "14:00",
        "local_arrival_time": "15:30",
        "duration": "02:00",
        "destination_airport_name": "Tehran Imam Khomeini International Airport",
        "destination_city": "Tehran",
        "destination_country": "Iran"
    },
    {
        "flight_number": "WZ4330",
        "aircraft_model": "",
        "airline_name": "Red Wings",
        "destination_iata": "AER",
        "local_departure_time": "14:35",
        "local_arrival_time": "15:10",
        "duration": "01:35",
        "destination_airport_name": "Sochi International Airport",
        "destination_city": "Sochi",
        "destination_country": "Russia"
    },
    {
        "flight_number": "SU1867",
        "aircraft_model": "",
        "airline_name": "Aeroflot",
        "destination_iata": "SVO",
        "local_departure_time": "15:10",
        "local_arrival_time": "17:50",
        "duration": "03:40",
        "destination_airport_name": "Moscow Sheremetyevo International Airport",
        "destination_city": "Moscow",
        "destination_country": "Russia"
    },
    {
        "flight_number": "S75592",
        "aircraft_model": "",
        "airline_name": "S7 Airlines",
        "destination_iata": "OVB",
        "local_departure_time": "15:10",
        "local_arrival_time": "22:40",
        "duration": "04:30",
        "destination_airport_name": "Novosibirsk Tolmachevo Airport",
        "destination_city": "Novosibirsk",
        "destination_country": "Russia"
    },
    {
        "flight_number": "SU1867",
        "aircraft_model": "",
        "airline_name": "Aeroflot",
        "destination_iata": "SVO",
        "local_departure_time": "15:10",
        "local_arrival_time": "17:45",
        "duration": "03:35",
        "destination_airport_name": "Moscow Sheremetyevo International Airport",
        "destination_city": "Moscow",
        "destination_country": "Russia"
    },
    {
        "flight_number": "TO7499",
        "aircraft_model": "",
        "airline_name": "Transavia France",
        "destination_iata": "ORY",
        "local_departure_time": "15:30",
        "local_arrival_time": "18:50",
        "duration": "05:20",
        "destination_airport_name": "Paris Orly Airport",
        "destination_city": "Paris",
        "destination_country": "France"
    },
    {
        "flight_number": "LH8317",
        "aircraft_model": "",
        "airline_name": "Lufthansa",
        "destination_iata": "FRA",
        "local_departure_time": "15:35",
        "local_arrival_time": "18:15",
        "duration": "04:40",
        "destination_airport_name": "Frankfurt Airport",
        "destination_city": "Frankfurt",
        "destination_country": "Germany"
    },
    {
        "flight_number": "SU6924",
        "aircraft_model": "Airbus A319-111",
        "airline_name": "Rossiya",
        "destination_iata": "LED",
        "local_departure_time": "15:50",
        "local_arrival_time": "18:55",
        "duration": "04:05",
        "destination_airport_name": "St. Petersburg Pulkovo Airport",
        "destination_city": "St. Petersburg",
        "destination_country": "Russia"
    },
    {
        "flight_number": "SU6924",
        "aircraft_model": "",
        "airline_name": "Aeroflot",
        "destination_iata": "LED",
        "local_departure_time": "15:50",
        "local_arrival_time": "18:50",
        "duration": "04:00",
        "destination_airport_name": "St. Petersburg Pulkovo Airport",
        "destination_city": "St. Petersburg",
        "destination_country": "Russia"
    },
    {
        "flight_number": "3F485",
        "aircraft_model": "Airbus A320-214",
        "airline_name": "Sky Angkor Airlines",
        "destination_iata": "CGN",
        "local_departure_time": "16:05",
        "local_arrival_time": "19:00",
        "duration": "04:55",
        "destination_airport_name": "Cologne Bonn Airport",
        "destination_city": "Cologne",
        "destination_country": "Germany"
    },
    {
        "flight_number": "3F927",
        "aircraft_model": "Airbus A320-232",
        "airline_name": "FlyOne",
        "destination_iata": "CDG",
        "local_departure_time": "16:05",
        "local_arrival_time": "19:20",
        "duration": "05:15",
        "destination_airport_name": "Paris Charles de Gaulle Airport",
        "destination_city": "Paris",
        "destination_country": "France"
    },
    {
        "flight_number": "3F545",
        "aircraft_model": "",
        "airline_name": "FlyOne Armenia",
        "destination_iata": "BRU",
        "local_departure_time": "16:05",
        "local_arrival_time": "19:20",
        "duration": "05:15",
        "destination_airport_name": "Brussels Airport",
        "destination_city": "Brussels",
        "destination_country": "Belgium"
    },
    {
        "flight_number": "WZ4678",
        "aircraft_model": "",
        "airline_name": "Red Wings",
        "destination_iata": "KZN",
        "local_departure_time": "16:15",
        "local_arrival_time": "18:15",
        "duration": "03:00",
        "destination_airport_name": "Kazan International Airport",
        "destination_city": "Kazan",
        "destination_country": "Russia"
    },
    {
        "flight_number": "3F231",
        "aircraft_model": "Airbus A320-232",
        "airline_name": "FlyOne",
        "destination_iata": "BCN",
        "local_departure_time": "16:25",
        "local_arrival_time": "19:50",
        "duration": "05:25",
        "destination_airport_name": "Barcelona El Prat Airport",
        "destination_city": "Barcelona",
        "destination_country": "Spain"
    },
    {
        "flight_number": "3F315",
        "aircraft_model": "",
        "airline_name": "FlyOne Armenia",
        "destination_iata": "DME",
        "local_departure_time": "16:30",
        "local_arrival_time": "18:30",
        "duration": "03:00",
        "destination_airport_name": "Moscow Domodedovo International Airport",
        "destination_city": "Moscow",
        "destination_country": "Russia"
    },
    {
        "flight_number": "TO7499",
        "aircraft_model": "Boeing 737-8K2",
        "airline_name": "Transavia",
        "destination_iata": "ORY",
        "local_departure_time": "16:35",
        "local_arrival_time": "19:55",
        "duration": "05:20",
        "destination_airport_name": "Paris Orly Airport",
        "destination_city": "Paris",
        "destination_country": "France"
    },
    {
        "flight_number": "3F583",
        "aircraft_model": "",
        "airline_name": "FlyOne Armenia",
        "destination_iata": "TBS",
        "local_departure_time": "17:05",
        "local_arrival_time": "17:50",
        "duration": "00:45",
        "destination_airport_name": "Tbilisi International Airport",
        "destination_city": "Tbilisi",
        "destination_country": "Georgia"
    },
    {
        "flight_number": "3F931",
        "aircraft_model": "",
        "airline_name": "FlyOne Armenia",
        "destination_iata": "NCE",
        "local_departure_time": "17:05",
        "local_arrival_time": "19:50",
        "duration": "04:45",
        "destination_airport_name": "Nice Cote d'Azur Airport",
        "destination_city": "Nice",
        "destination_country": "France"
    },
    {
        "flight_number": "TO7499",
        "aircraft_model": "",
        "airline_name": "Transavia France",
        "destination_iata": "ORY",
        "local_departure_time": "17:05",
        "local_arrival_time": "20:25",
        "duration": "05:20",
        "destination_airport_name": "Paris Orly Airport",
        "destination_city": "Paris",
        "destination_country": "France"
    },
    {
        "flight_number": "JI142",
        "aircraft_model": "",
        "airline_name": "Armenian Airlines",
        "destination_iata": "KZN",
        "local_departure_time": "17:20",
        "local_arrival_time": "19:15",
        "duration": "02:55",
        "destination_airport_name": "Kazan International Airport",
        "destination_city": "Kazan",
        "destination_country": "Russia"
    },
    {
        "flight_number": "G9245",
        "aircraft_model": "",
        "airline_name": "Air Arabia",
        "destination_iata": "SHJ",
        "local_departure_time": "17:25",
        "local_arrival_time": "20:20",
        "duration": "02:55",
        "destination_airport_name": "Sharjah International Airport",
        "destination_city": "Sharjah",
        "destination_country": "United Arab Emirates"
    },
    {
        "flight_number": "3F245",
        "aircraft_model": "",
        "airline_name": "FlyOne Armenia",
        "destination_iata": "MXP",
        "local_departure_time": "17:30",
        "local_arrival_time": "20:10",
        "duration": "04:40",
        "destination_airport_name": "Milan Malpensa Airport",
        "destination_city": "Milan",
        "destination_country": "Italy"
    },
    {
        "flight_number": "3F349",
        "aircraft_model": "",
        "airline_name": "FlyOne Armenia",
        "destination_iata": "AER",
        "local_departure_time": "17:35",
        "local_arrival_time": "17:45",
        "duration": "01:10",
        "destination_airport_name": "Sochi International Airport",
        "destination_city": "Sochi",
        "destination_country": "Russia"
    },
    {
        "flight_number": "WZ1356",
        "aircraft_model": "",
        "airline_name": "Red Wings",
        "destination_iata": "KUF",
        "local_departure_time": "17:35",
        "local_arrival_time": "20:20",
        "duration": "02:45",
        "destination_airport_name": "Samara Kurumoch International Airport",
        "destination_city": "Samara",
        "destination_country": "Russia"
    },
    {
        "flight_number": "3F333",
        "aircraft_model": "Airbus A320-232",
        "airline_name": "FlyOne",
        "destination_iata": "LED",
        "local_departure_time": "18:00",
        "local_arrival_time": "21:00",
        "duration": "04:00",
        "destination_airport_name": "St. Petersburg Pulkovo Airport",
        "destination_city": "St. Petersburg",
        "destination_country": "Russia"
    },
    {
        "flight_number": "W64570",
        "aircraft_model": "Airbus A321-231",
        "airline_name": "Wizz Air",
        "destination_iata": "LCA",
        "local_departure_time": "18:15",
        "local_arrival_time": "19:30",
        "duration": "02:15",
        "destination_airport_name": "Larnaca International Airport",
        "destination_city": "Larnaca",
        "destination_country": "Cyprus"
    },
    {
        "flight_number": "A47030",
        "aircraft_model": "",
        "airline_name": "Azimuth",
        "destination_iata": "VKO",
        "local_departure_time": "18:30",
        "local_arrival_time": "20:50",
        "duration": "03:20",
        "destination_airport_name": "Moscow Vnukovo International Airport",
        "destination_city": "Moscow",
        "destination_country": "Russia"
    },
    {
        "flight_number": "U62950",
        "aircraft_model": "",
        "airline_name": "Ural Airlines",
        "destination_iata": "SVX",
        "local_departure_time": "18:40",
        "local_arrival_time": "23:00",
        "duration": "03:20",
        "destination_airport_name": "Yekaterinburg Koltsovo International Airport",
        "destination_city": "Yekaterinburg",
        "destination_country": "Russia"
    },
    {
        "flight_number": "SU685",
        "aircraft_model": "",
        "airline_name": "Aeroflot",
        "destination_iata": "SVX",
        "local_departure_time": "18:45",
        "local_arrival_time": "23:05",
        "duration": "03:20",
        "destination_airport_name": "Yekaterinburg Koltsovo International Airport",
        "destination_city": "Yekaterinburg",
        "destination_country": "Russia"
    },
    {
        "flight_number": "U62950",
        "aircraft_model": "",
        "airline_name": "Ural Airlines",
        "destination_iata": "SVX",
        "local_departure_time": "18:55",
        "local_arrival_time": "23:15",
        "duration": "03:20",
        "destination_airport_name": "Yekaterinburg Koltsovo International Airport",
        "destination_city": "Yekaterinburg",
        "destination_country": "Russia"
    },
    {
        "flight_number": "5G100",
        "aircraft_model": "",
        "airline_name": "Shirak Avia",
        "destination_iata": "UFA",
        "local_departure_time": "19:05",
        "local_arrival_time": "22:45",
        "duration": "02:40",
        "destination_airport_name": "Ufa International Airport",
        "destination_city": "Ufa",
        "destination_country": "Russia"
    },
    {
        "flight_number": "U62950",
        "aircraft_model": "",
        "airline_name": "Ural Airlines",
        "destination_iata": "SVX",
        "local_departure_time": "19:15",
        "local_arrival_time": "23:35",
        "duration": "03:20",
        "destination_airport_name": "Yekaterinburg Koltsovo International Airport",
        "destination_city": "Yekaterinburg",
        "destination_country": "Russia"
    },
    {
        "flight_number": "WZ4330",
        "aircraft_model": "",
        "airline_name": "Red Wings",
        "destination_iata": "AER",
        "local_departure_time": "19:35",
        "local_arrival_time": "20:00",
        "duration": "01:25",
        "destination_airport_name": "Sochi International Airport",
        "destination_city": "Sochi",
        "destination_country": "Russia"
    },
    {
        "flight_number": "5W7188",
        "aircraft_model": "",
        "airline_name": "Wizz Air Abu Dhabi",
        "destination_iata": "AUH",
        "local_departure_time": "20:05",
        "local_arrival_time": "23:15",
        "duration": "03:10",
        "destination_airport_name": "Abu Dhabi Zayed International Airport",
        "destination_city": "Abu Dhabi",
        "destination_country": "United Arab Emirates"
    },
    {
        "flight_number": "TO7501",
        "aircraft_model": "Boeing 737-8K2",
        "airline_name": "Transavia",
        "destination_iata": "LYS",
        "local_departure_time": "20:10",
        "local_arrival_time": "23:00",
        "duration": "04:50",
        "destination_airport_name": "Lyon Saint Exupery Airport",
        "destination_city": "Lyon",
        "destination_country": "France"
    },
    {
        "flight_number": "SU1863",
        "aircraft_model": "",
        "airline_name": "Aeroflot",
        "destination_iata": "SVO",
        "local_departure_time": "20:50",
        "local_arrival_time": "23:30",
        "duration": "03:40",
        "destination_airport_name": "Moscow Sheremetyevo International Airport",
        "destination_city": "Moscow",
        "destination_country": "Russia"
    },
    {
        "flight_number": "SU6950",
        "aircraft_model": "",
        "airline_name": "Aeroflot",
        "destination_iata": "KUF",
        "local_departure_time": "20:50",
        "local_arrival_time": "23:20",
        "duration": "02:30",
        "destination_airport_name": "Samara Kurumoch International Airport",
        "destination_city": "Samara",
        "destination_country": "Russia"
    },
    {
        "flight_number": "SU6950",
        "aircraft_model": "",
        "airline_name": "Aeroflot",
        "destination_iata": "KUF",
        "local_departure_time": "20:50",
        "local_arrival_time": "23:30",
        "duration": "02:40",
        "destination_airport_name": "Samara Kurumoch International Airport",
        "destination_city": "Samara",
        "destination_country": "Russia"
    },
    {
        "flight_number": "SU6742",
        "aircraft_model": "",
        "airline_name": "Aeroflot",
        "destination_iata": "AER",
        "local_departure_time": "21:10",
        "local_arrival_time": "21:30",
        "duration": "01:20",
        "destination_airport_name": "Sochi International Airport",
        "destination_city": "Sochi",
        "destination_country": "Russia"
    },
    {
        "flight_number": "W64612",
        "aircraft_model": "",
        "airline_name": "Wizz Air",
        "destination_iata": "LCA",
        "local_departure_time": "21:25",
        "local_arrival_time": "22:40",
        "duration": "02:15",
        "destination_airport_name": "Larnaca International Airport",
        "destination_city": "Larnaca",
        "destination_country": "Cyprus"
    },
    {
        "flight_number": "3F323",
        "aircraft_model": "",
        "airline_name": "FlyOne Armenia",
        "destination_iata": "VKO",
        "local_departure_time": "22:00",
        "local_arrival_time": "00:05 (+1)",
        "duration": "03:05",
        "destination_airport_name": "Moscow Vnukovo International Airport",
        "destination_city": "Moscow",
        "destination_country": "Russia"
    },
    {
        "flight_number": "W46456",
        "aircraft_model": "Airbus A321-271NX",
        "airline_name": "Wizz Air",
        "destination_iata": "MXP",
        "local_departure_time": "22:10",
        "local_arrival_time": "00:45 (+1)",
        "duration": "04:35",
        "destination_airport_name": "Milan Malpensa Airport",
        "destination_city": "Milan",
        "destination_country": "Italy"
    },
    {
        "flight_number": "W46176",
        "aircraft_model": "",
        "airline_name": "Wizz Air Malta",
        "destination_iata": "FCO",
        "local_departure_time": "22:25",
        "local_arrival_time": "00:40 (+1)",
        "duration": "04:15",
        "destination_airport_name": "Rome Leonardo da Vinci Fiumicino Airport",
        "destination_city": "Rome",
        "destination_country": "Italy"
    },
    {
        "flight_number": "W46456",
        "aircraft_model": "",
        "airline_name": "Wizz Air Malta",
        "destination_iata": "MXP",
        "local_departure_time": "22:55",
        "local_arrival_time": "01:30 (+1)",
        "duration": "04:35",
        "destination_airport_name": "Milan Malpensa Airport",
        "destination_city": "Milan",
        "destination_country": "Italy"
    },
    {
        "flight_number": "W46764",
        "aircraft_model": "Airbus A321-271NX",
        "airline_name": "Wizz Air",
        "destination_iata": "VCE",
        "local_departure_time": "22:55",
        "local_arrival_time": "01:10 (+1)",
        "duration": "04:15",
        "destination_airport_name": "Venice Marco Polo Airport",
        "destination_city": "Venice",
        "destination_country": "Italy"
    },
    {
        "flight_number": "RLA7778",
        "aircraft_model": "Bombardier Challenger 650",
        "airline_name": "Private owner",
        "destination_iata": "VKO",
        "local_departure_time": "23:00",
        "local_arrival_time": "01:11 (+1)",
        "duration": "03:11",
        "destination_airport_name": "Moscow Vnukovo International Airport",
        "destination_city": "Moscow",
        "destination_country": "Russia"
    },
    {
        "flight_number": "SU6742",
        "aircraft_model": "",
        "airline_name": "Aeroflot",
        "destination_iata": "AER",
        "local_departure_time": "23:35",
        "local_arrival_time": "23:35",
        "duration": "01:00",
        "destination_airport_name": "Sochi International Airport",
        "destination_city": "Sochi",
        "destination_country": "Russia"
    },
    {
        "flight_number": "5G709",
        "aircraft_model": "",
        "airline_name": "Shirak Avia",
        "destination_iata": "SVO",
        "local_departure_time": "23:40",
        "local_arrival_time": "02:10 (+1)",
        "duration": "03:30",
        "destination_airport_name": "Moscow Sheremetyevo International Airport",
        "destination_city": "Moscow",
        "destination_country": "Russia"
    },
    {
        "flight_number": "W64424",
        "aircraft_model": "",
        "airline_name": "Wizz Air",
        "destination_iata": "SOF",
        "local_departure_time": "23:40",
        "local_arrival_time": "01:35 (+1)",
        "duration": "02:55",
        "destination_airport_name": "Sofia Vasil Levski Airport",
        "destination_city": "Sofia",
        "destination_country": "Bulgaria"
    }
]